LICENSE
README.md
setup.py
AKFlask.egg-info/PKG-INFO
AKFlask.egg-info/SOURCES.txt
AKFlask.egg-info/dependency_links.txt
AKFlask.egg-info/requires.txt
AKFlask.egg-info/top_level.txt
akflask/__init__.py
akflask/akflask.py
akflask.egg-info/PKG-INFO
akflask.egg-info/SOURCES.txt
akflask.egg-info/dependency_links.txt
akflask.egg-info/requires.txt
akflask.egg-info/top_level.txt